damv1templateprojectk8salert/__init__.py
damv1templateprojectk8salert/mytemplateproject.py
damv1templateprojectk8salert-0.0.53.dist-info/METADATA
damv1templateprojectk8salert-0.0.53.dist-info/WHEEL
damv1templateprojectk8salert-0.0.53.dist-info/top_level.txt
damv1templateprojectk8salert-0.0.53.dist-info/RECORD
