Metadata-Version: 2.1
Name: damv1templateprojectk8salert
Version: 0.0.53
Summary: template project k8s alert package
Home-page: UNKNOWN
Author: dhonyabumuhammad (Bekasi)
Author-email: <dhony.priniardi.m@gmail.com>
License: UNKNOWN
Keywords: templateprojectk8salert
Platform: UNKNOWN
Classifier: Development Status :: 1 - Planning
Classifier: Intended Audience :: Developers
Classifier: Programming Language :: Python :: 3
Classifier: Operating System :: Unix
Classifier: Operating System :: MacOS :: MacOS X
Classifier: Operating System :: Microsoft :: Windows
